oremda/engine/__init__.py
oremda/engine/cli.py
oremda/engine/config.py
oremda/engine/context.py
oremda/engine/rpc/client.py
oremda/engine/rpc/displays/__init__.py
oremda/engine/rpc/messages/__init__.py
oremda/engine/rpc/models/__init__.py
oremda/engine/rpc/observer/__init__.py
oremda/engine/rpc/serialization.py
oremda_engine-0.0.4.dist-info/entry_points.txt
oremda_engine-0.0.4.dist-info/WHEEL
oremda_engine-0.0.4.dist-info/METADATA
oremda_engine-0.0.4.dist-info/RECORD
